explain_log/__init__.py
explain_log/explainer.py
explain_log/main.py
explain_log/utils.py
explain_log-0.1.2.dist-info/licenses/LICENSE
explain_log-0.1.2.dist-info/METADATA
explain_log-0.1.2.dist-info/WHEEL
explain_log-0.1.2.dist-info/entry_points.txt
explain_log-0.1.2.dist-info/top_level.txt
explain_log-0.1.2.dist-info/RECORD
