Metadata-Version: 2.4
Name: explain-log
Version: 0.1.2
Summary: Explain your DevOps logs instantly using OpenAI with a colorful CLI.
Home-page: https://github.com/yourgithub/explain-log
Author: Tasrie IT Services
Author-email: info@tasrieit.com
Project-URL: Bug Tracker, https://github.com/tasrieitservices/explain-log/issues
Classifier: Programming Language :: Python :: 3
Classifier: License :: OSI Approved :: MIT License
Classifier: Operating System :: OS Independent
Requires-Python: >=3.8
License-File: LICENSE
Requires-Dist: openai
Requires-Dist: click
Requires-Dist: rich
Requires-Dist: python-dotenv
Dynamic: author
Dynamic: author-email
Dynamic: classifier
Dynamic: description
Dynamic: description-content-type
Dynamic: home-page
Dynamic: license-file
Dynamic: project-url
Dynamic: requires-dist
Dynamic: requires-python
Dynamic: summary
